up_ff/ff_planner.py
up_ff/FF/ff
up_ff-0.0.0.dist-info/LICENSE
up_ff-0.0.0.dist-info/METADATA
up_ff-0.0.0.dist-info/WHEEL
up_ff-0.0.0.dist-info/top_level.txt
up_ff-0.0.0.dist-info/RECORD
