Metadata-Version: 2.1
Name: up-ff
Version: 0.0.0
Summary: up_ff
Home-page: UNKNOWN
Author: UNIBS Team
Author-email: enrico.scala@unibs.it
License: APACHE
Platform: UNKNOWN
